<?xml version="1.0" encoding="UTF-8"?>
<!DOCTYPE mapper PUBLIC "-//mybatis.org//DTD Mapper 3.0//EN" "http://mybatis.org/dtd/mybatis-3-mapper.dtd">
<mapper namespace="com.sinitek.newtrade.pay.ccbebs.dao.DsOrderMapper">
  <resultMap id="BaseResultMap" type="com.sinitek.newtrade.pay.ccbebs.dao.DsOrder">
    <!--
      WARNING - @mbggenerated
      This element is automatically generated by MyBatis Generator, do not modify.
      This element was generated on Fri Apr 01 16:46:14 CST 2016.
    -->
    <result column="REQUESTNO" jdbcType="VARCHAR" property="requestno" />
    <result column="BALANCE" jdbcType="DECIMAL" property="balance" />
    <result column="CAPITALMODE" jdbcType="CHAR" property="capitalmode" />
    <result column="BANKSTATE" jdbcType="CHAR" property="bankstate" />
    <result column="BANKORDERNO" jdbcType="VARCHAR" property="bankorderno" />
    <result column="ACCEPTDATE" jdbcType="VARCHAR" property="acceptdate" />
    <result column="BUSINTYPE" jdbcType="CHAR" property="busintype" />
    <result column="CREATETIME" jdbcType="TIMESTAMP" property="createtime" />
    <result column="UPDATETIME" jdbcType="TIMESTAMP" property="updatetime" />
    <result column="TRADEDATE" jdbcType="VARCHAR" property="tradedate" />
  </resultMap>
  <sql id="Example_Where_Clause">
    <!--
      WARNING - @mbggenerated
      This element is automatically generated by MyBatis Generator, do not modify.
      This element was generated on Fri Apr 01 16:46:14 CST 2016.
    -->
    <where>
      <foreach collection="oredCriteria" item="criteria" separator="or">
        <if test="criteria.valid">
          <trim prefix="(" prefixOverrides="and" suffix=")">
            <foreach collection="criteria.criteria" item="criterion">
              <choose>
                <when test="criterion.noValue">
                  and ${criterion.condition}
                </when>
                <when test="criterion.singleValue">
                  and ${criterion.condition} #{criterion.value}
                </when>
                <when test="criterion.betweenValue">
                  and ${criterion.condition} #{criterion.value} and #{criterion.secondValue}
                </when>
                <when test="criterion.listValue">
                  and ${criterion.condition}
                  <foreach close=")" collection="criterion.value" item="listItem" open="(" separator=",">
                    #{listItem}
                  </foreach>
                </when>
              </choose>
            </foreach>
          </trim>
        </if>
      </foreach>
    </where>
  </sql>
  <sql id="Update_By_Example_Where_Clause">
    <!--
      WARNING - @mbggenerated
      This element is automatically generated by MyBatis Generator, do not modify.
      This element was generated on Fri Apr 01 16:46:14 CST 2016.
    -->
    <where>
      <foreach collection="example.oredCriteria" item="criteria" separator="or">
        <if test="criteria.valid">
          <trim prefix="(" prefixOverrides="and" suffix=")">
            <foreach collection="criteria.criteria" item="criterion">
              <choose>
                <when test="criterion.noValue">
                  and ${criterion.condition}
                </when>
                <when test="criterion.singleValue">
                  and ${criterion.condition} #{criterion.value}
                </when>
                <when test="criterion.betweenValue">
                  and ${criterion.condition} #{criterion.value} and #{criterion.secondValue}
                </when>
                <when test="criterion.listValue">
                  and ${criterion.condition}
                  <foreach close=")" collection="criterion.value" item="listItem" open="(" separator=",">
                    #{listItem}
                  </foreach>
                </when>
              </choose>
            </foreach>
          </trim>
        </if>
      </foreach>
    </where>
  </sql>
  <sql id="Base_Column_List">
    <!--
      WARNING - @mbggenerated
      This element is automatically generated by MyBatis Generator, do not modify.
      This element was generated on Fri Apr 01 16:46:14 CST 2016.
    -->
    REQUESTNO, BALANCE, CAPITALMODE, BANKSTATE, BANKORDERNO, ACCEPTDATE, BUSINTYPE, CREATETIME, 
    UPDATETIME, TRADEDATE
  </sql>
  <select id="selectByExample" parameterType="com.sinitek.newtrade.pay.ccbebs.dao.DsOrderExample" resultMap="BaseResultMap">
    <!--
      WARNING - @mbggenerated
      This element is automatically generated by MyBatis Generator, do not modify.
      This element was generated on Fri Apr 01 16:46:14 CST 2016.
    -->
    select
    <if test="distinct">
      distinct
    </if>
    <include refid="Base_Column_List" />
    from DS_ORDER
    <if test="_parameter != null">
      <include refid="Example_Where_Clause" />
    </if>
    <if test="orderByClause != null">
      order by ${orderByClause}
    </if>
  </select>
  <delete id="deleteByExample" parameterType="com.sinitek.newtrade.pay.ccbebs.dao.DsOrderExample">
    <!--
      WARNING - @mbggenerated
      This element is automatically generated by MyBatis Generator, do not modify.
      This element was generated on Fri Apr 01 16:46:14 CST 2016.
    -->
    delete from DS_ORDER
    <if test="_parameter != null">
      <include refid="Example_Where_Clause" />
    </if>
  </delete>
  <insert id="insert" parameterType="com.sinitek.newtrade.pay.ccbebs.dao.DsOrder">
    <!--
      WARNING - @mbggenerated
      This element is automatically generated by MyBatis Generator, do not modify.
      This element was generated on Fri Apr 01 16:46:14 CST 2016.
    -->
    insert into DS_ORDER (REQUESTNO, BALANCE, CAPITALMODE, 
      BANKSTATE, BANKORDERNO, ACCEPTDATE, 
      BUSINTYPE, CREATETIME, UPDATETIME, 
      TRADEDATE)
    values (#{requestno,jdbcType=VARCHAR}, #{balance,jdbcType=DECIMAL}, #{capitalmode,jdbcType=CHAR}, 
      #{bankstate,jdbcType=CHAR}, #{bankorderno,jdbcType=VARCHAR}, #{acceptdate,jdbcType=VARCHAR}, 
      #{busintype,jdbcType=CHAR}, #{createtime,jdbcType=TIMESTAMP}, #{updatetime,jdbcType=TIMESTAMP}, 
      #{tradedate,jdbcType=VARCHAR})
  </insert>
  <insert id="insertSelective" parameterType="com.sinitek.newtrade.pay.ccbebs.dao.DsOrder">
    <!--
      WARNING - @mbggenerated
      This element is automatically generated by MyBatis Generator, do not modify.
      This element was generated on Fri Apr 01 16:46:14 CST 2016.
    -->
    insert into DS_ORDER
    <trim prefix="(" suffix=")" suffixOverrides=",">
      <if test="requestno != null">
        REQUESTNO,
      </if>
      <if test="balance != null">
        BALANCE,
      </if>
      <if test="capitalmode != null">
        CAPITALMODE,
      </if>
      <if test="bankstate != null">
        BANKSTATE,
      </if>
      <if test="bankorderno != null">
        BANKORDERNO,
      </if>
      <if test="acceptdate != null">
        ACCEPTDATE,
      </if>
      <if test="busintype != null">
        BUSINTYPE,
      </if>
      <if test="createtime != null">
        CREATETIME,
      </if>
      <if test="updatetime != null">
        UPDATETIME,
      </if>
      <if test="tradedate != null">
        TRADEDATE,
      </if>
    </trim>
    <trim prefix="values (" suffix=")" suffixOverrides=",">
      <if test="requestno != null">
        #{requestno,jdbcType=VARCHAR},
      </if>
      <if test="balance != null">
        #{balance,jdbcType=DECIMAL},
      </if>
      <if test="capitalmode != null">
        #{capitalmode,jdbcType=CHAR},
      </if>
      <if test="bankstate != null">
        #{bankstate,jdbcType=CHAR},
      </if>
      <if test="bankorderno != null">
        #{bankorderno,jdbcType=VARCHAR},
      </if>
      <if test="acceptdate != null">
        #{acceptdate,jdbcType=VARCHAR},
      </if>
      <if test="busintype != null">
        #{busintype,jdbcType=CHAR},
      </if>
      <if test="createtime != null">
        #{createtime,jdbcType=TIMESTAMP},
      </if>
      <if test="updatetime != null">
        #{updatetime,jdbcType=TIMESTAMP},
      </if>
      <if test="tradedate != null">
        #{tradedate,jdbcType=VARCHAR},
      </if>
    </trim>
  </insert>
  <select id="countByExample" parameterType="com.sinitek.newtrade.pay.ccbebs.dao.DsOrderExample" resultType="java.lang.Integer">
    <!--
      WARNING - @mbggenerated
      This element is automatically generated by MyBatis Generator, do not modify.
      This element was generated on Fri Apr 01 16:46:14 CST 2016.
    -->
    select count(*) from DS_ORDER
    <if test="_parameter != null">
      <include refid="Example_Where_Clause" />
    </if>
  </select>
  <update id="updateByExampleSelective" parameterType="map">
    <!--
      WARNING - @mbggenerated
      This element is automatically generated by MyBatis Generator, do not modify.
      This element was generated on Fri Apr 01 16:46:14 CST 2016.
    -->
    update DS_ORDER
    <set>
      <if test="record.requestno != null">
        REQUESTNO = #{record.requestno,jdbcType=VARCHAR},
      </if>
      <if test="record.balance != null">
        BALANCE = #{record.balance,jdbcType=DECIMAL},
      </if>
      <if test="record.capitalmode != null">
        CAPITALMODE = #{record.capitalmode,jdbcType=CHAR},
      </if>
      <if test="record.bankstate != null">
        BANKSTATE = #{record.bankstate,jdbcType=CHAR},
      </if>
      <if test="record.bankorderno != null">
        BANKORDERNO = #{record.bankorderno,jdbcType=VARCHAR},
      </if>
      <if test="record.acceptdate != null">
        ACCEPTDATE = #{record.acceptdate,jdbcType=VARCHAR},
      </if>
      <if test="record.busintype != null">
        BUSINTYPE = #{record.busintype,jdbcType=CHAR},
      </if>
      <if test="record.createtime != null">
        CREATETIME = #{record.createtime,jdbcType=TIMESTAMP},
      </if>
      <if test="record.updatetime != null">
        UPDATETIME = #{record.updatetime,jdbcType=TIMESTAMP},
      </if>
      <if test="record.tradedate != null">
        TRADEDATE = #{record.tradedate,jdbcType=VARCHAR},
      </if>
    </set>
    <if test="_parameter != null">
      <include refid="Update_By_Example_Where_Clause" />
    </if>
  </update>
  <update id="updateByExample" parameterType="map">
    <!--
      WARNING - @mbggenerated
      This element is automatically generated by MyBatis Generator, do not modify.
      This element was generated on Fri Apr 01 16:46:14 CST 2016.
    -->
    update DS_ORDER
    set REQUESTNO = #{record.requestno,jdbcType=VARCHAR},
      BALANCE = #{record.balance,jdbcType=DECIMAL},
      CAPITALMODE = #{record.capitalmode,jdbcType=CHAR},
      BANKSTATE = #{record.bankstate,jdbcType=CHAR},
      BANKORDERNO = #{record.bankorderno,jdbcType=VARCHAR},
      ACCEPTDATE = #{record.acceptdate,jdbcType=VARCHAR},
      BUSINTYPE = #{record.busintype,jdbcType=CHAR},
      CREATETIME = #{record.createtime,jdbcType=TIMESTAMP},
      UPDATETIME = #{record.updatetime,jdbcType=TIMESTAMP},
      TRADEDATE = #{record.tradedate,jdbcType=VARCHAR}
    <if test="_parameter != null">
      <include refid="Update_By_Example_Where_Clause" />
    </if>
  </update>
</mapper>